[{"name": "LETSCOM Bluetooth Headphones V5.0 IPX7 Waterproof, Wireless Sport Earphones", "price": 1799, "status": "Brand New", "shipping": 0, "free_returns": false, "items_sold": null}, {"name": "Bluetooth Earbuds for iphone Samsung Android Wireless Earphone IPX7 Waterproof  ", "price": 1999, "status": "Brand New", "shipping": null, "free_returns": true, "items_sold": null}, {"name": "Wireless Bluetooth Headphones Super Bass Foldable Stereo Earphones Headsets Mic ", "price": 1699, "status": "Brand New", "shipping": null, "free_returns": true, "items_sold": null}, {"name": "Bluetooth Earbuds for iPhone Samsung Android Wireless Earphone Waterproof", "price": 1699, "status": "Brand New", "shipping": 0, "free_returns": true, "items_sold": null}, {"name": "JBL TUNE 500BT Wireless Bluetooth On-ear Headphones", "price": 1995, "status": "Brand New", "shipping": 0, "free_returns": true, "items_sold": 0}, {"name": "Art+Sound Metallic On-Ear Wired Headphones with Built-In Mic + Foldable Headband", "price": 999, "status": "Brand New", "shipping": 0, "free_returns": false, "items_sold": null}, {"name": "JBL Endurance PEAK Waterproof Bluetooth Wireless In-Ear Sport Headphones, Black", "price": 3995, "status": "Brand New", "shipping": 0, "free_returns": true, "items_sold": 0}, {"name": "Bose Sport Earbuds, Certified Refurbished", "price": 11900, "status": null, "shipping": null, "free_returns": false, "items_sold": 0}, {"name": "Skullcandy HESH 2 Wireless Headphones with Mic (Certified Refurbished)-BLACK", "price": 2799, "status": null, "shipping": null, "free_returns": false, "items_sold": 0}, {"name": "Skullcandy JIB TRUE Wireless In-Ear Headphones (Certified Refurbished)", "price": 1555, "status": null, "shipping": null, "free_returns": false, "items_sold": 0}, {"name": "Bose QuietComfort Earbuds, Certified Refurbished", "price": 17900, "status": null, "shipping": null, "free_returns": false, "items_sold": 0}, {"name": "Skullcandy CRUSHER Wireless Headphones w/Mic (Certified Refurbished)-BLACK", "price": 6199, "status": null, "shipping": null, "free_returns": false, "items_sold": 0}, {"name": "Bose Frames Alto, Certified Refurbished", "price": 9900, "status": null, "shipping": null, "free_returns": false, "items_sold": 0}, {"name": "Skullcandy INDY FUEL True Wireless Earbuds (Certified Refurbished) BLACK", "price": 2499, "status": null, "shipping": null, "free_returns": false, "items_sold": 0}, {"name": "Sony WH-1000XM4 Wireless Noise-Cancelling Over-the-Ear Headphones - Black", "price": 19999, "status": null, "shipping": 0, "free_returns": false, "items_sold": 0}, {"name": "Bose Sport Earbuds, Certified Refurbished", "price": 11900, "status": "Certified - Refurbished", "shipping": null, "free_returns": true, "items_sold": 0}, {"name": "JLab Studio Wired On-Ear Headphones - Black", "price": 1199, "status": "New (Other)", "shipping": null, "free_returns": false, "items_sold": 1232}, {"name": "Sony MDRZX110/BLK Stereo Headphones-Black", "price": 1595, "status": "Brand New", "shipping": 0, "free_returns": true, "items_sold": 3731}, {"name": "Replacement Beats by Dr. Dre Earbud or Charging Case Powerbeats Pro MV6Y2LL/A", "price": 6499, "status": "Pre-Owned", "shipping": null, "free_returns": true, "items_sold": 111}, {"name": "AKG by Harman N60NC Wireless Noise-cancelling Headphones, Black", "price": 5995, "status": "Brand New", "shipping": 0, "free_returns": true, "items_sold": 0}, {"name": "US Wireless Solo Pro 6 Beats Earphones Earbuds headphones Bluetooth Beats", "price": 2974, "status": "Brand New", "shipping": 0, "free_returns": true, "items_sold": null}, {"name": "Wireless Bluetooth Headphones Super Bass Foldable Stereo Earphones Headsets Mic ", "price": 1699, "status": "Brand New", "shipping": null, "free_returns": true, "items_sold": null}, {"name": "For iPhone 6 7 8 iPhone XS 11 12 13 Pro Max Wired Headphone Headset Earbuds Gift", "price": 899, "status": "Brand New", "shipping": 0, "free_returns": true, "items_sold": null}, {"name": "Wireless Earbuds Bluetooth 5.0 Waterproof Headphones for iPhone Samsung Android", "price": 1999, "status": "Brand New", "shipping": null, "free_returns": true, "items_sold": null}, {"name": "Delton Chroma Wired On-Ear Headphones with Mic, 3.5MM Jack, Foldable Lightweight", "price": 995, "status": "Brand New", "shipping": 0, "free_returns": false, "items_sold": null}, {"name": "Skullcandy HESH 2 Wireless Headphones with Mic (Certified Refurbished)-BLACK", "price": 2799, "status": "Certified - Refurbished", "shipping": null, "free_returns": true, "items_sold": 0}, {"name": "Bluetooth Earbuds for iphone Samsung Android Wireless Earphone IPX7 Waterproof", "price": 1499, "status": "Brand New", "shipping": null, "free_returns": true, "items_sold": null}, {"name": "Skullcandy JIB TRUE Wireless In-Ear Headphones (Certified Refurbished)", "price": 1555, "status": "Certified - Refurbished", "shipping": null, "free_returns": true, "items_sold": 0}, {"name": "JBL Tune 510BT Wireless Bluetooth On-Ear Headphones", "price": 2794, "status": "Brand New", "shipping": 0, "free_returns": false, "items_sold": null}, {"name": "JBL Free X Black True Wireless In-Ear Bluetooth Headphones", "price": 3995, "status": "Brand New", "shipping": null, "free_returns": true, "items_sold": 1005}, {"name": "Wireless Earbuds Waterproof Stereo Headsets Beats Tour 3 Bilateral Stereo TWS L2", "price": 2499, "status": "Brand New", "shipping": 0, "free_returns": true, "items_sold": null}, {"name": "Bose QuietComfort Earbuds, Certified Refurbished", "price": 17900, "status": "Certified - Refurbished", "shipping": null, "free_returns": true, "items_sold": 0}, {"name": "Bone Conduction Headset Bluetooth 5.0 Wireless Outdoor Sport Open Ear Headphones", "price": 1548, "status": "Brand New", "shipping": 0, "free_returns": true, "items_sold": null}, {"name": "JBL Tune 215TWS True Wireless Bluetooth In-Ear Headphones", "price": 3194, "status": "Brand New", "shipping": 0, "free_returns": false, "items_sold": 0}, {"name": "Bluetooth Headphones Wireless Foldable Stereo Earphones Super Bass Headset Mic  ", "price": 1299, "status": "Brand New", "shipping": null, "free_returns": true, "items_sold": null}, {"name": "Replacement Beats Studio Buds Totally Wireless Earphones Left Right Side or Case", "price": 4799, "status": "Pre-Owned", "shipping": null, "free_returns": true, "items_sold": 110}, {"name": "Wireless Earbuds for iphone Samsung Android Bluetooth Earphone IPX7 Waterproof", "price": 1999, "status": "Brand New", "shipping": null, "free_returns": true, "items_sold": null}, {"name": "Polaroid Bluetooth Wireless Headphones | Dynamic Stereo Headset with Microphone", "price": 1999, "status": "Brand New", "shipping": 0, "free_returns": false, "items_sold": null}, {"name": "Bluetooth 5.2 Bone Conduction Headset Wireless Outdoor Sport Open Ear Headphones", "price": 1299, "status": "Brand New", "shipping": 0, "free_returns": false, "items_sold": null}, {"name": "Apple Beats by Dr. Dre Flex 12 Hour All-Day Wireless Bluetooth In-Ear Headphones", "price": 2995, "status": "New (Other)", "shipping": 0, "free_returns": true, "items_sold": 89}, {"name": "Bose Frames Alto, Certified Refurbished", "price": 9900, "status": "Certified - Refurbished", "shipping": null, "free_returns": true, "items_sold": 0}, {"name": "JBL Tune 110 Black Headphones / Earbuds, New In SEALED Box!! Hands Free Calling!", "price": 1299, "status": "Brand New", "shipping": null, "free_returns": true, "items_sold": null}, {"name": "Bluetooth Earbuds Wireless Headphone Headset Noise Cancelling for Android/iOS", "price": 1484, "status": "Brand New", "shipping": 0, "free_returns": true, "items_sold": null}, {"name": "Beats by Dr. Dre | Solo3 Wireless On-Ear Headphones (Brand New, 14 Colors)", "price": 12999, "status": "Brand New", "shipping": null, "free_returns": true, "items_sold": 759}, {"name": "Bose Noise Cancelling Headphones 700, Certified Refurbished", "price": 27900, "status": "Certified - Refurbished", "shipping": null, "free_returns": true, "items_sold": 0}, {"name": "Bluetooth Headset 5.0 True Wireless Earphones Earbuds Headphones HiFi Sport", "price": 2499, "status": "Brand New", "shipping": 0, "free_returns": true, "items_sold": null}, {"name": "Wireless Bluetooth 5.0 Earbud Headset Hands Free Headphone for iPhone Samsung LG", "price": 1298, "status": "Brand New", "shipping": 0, "free_returns": true, "items_sold": null}, {"name": "Bone Conduction Headphones Bluetooth 5.0 Wireless Earbuds Outdoor Sport Headset", "price": 1516, "status": "Brand New", "shipping": 0, "free_returns": true, "items_sold": 838}, {"name": "TWS Wireless Earphones Earbuds Bluetooth Stereo Headphones For Phones Universal", "price": 899, "status": "Brand New", "shipping": 0, "free_returns": false, "items_sold": null}, {"name": "Skullcandy CRUSHER Wireless Headphones w/Mic (Certified Refurbished)-BLACK", "price": 6199, "status": "Certified - Refurbished", "shipping": null, "free_returns": true, "items_sold": 0}, {"name": "Bose QuietComfort 35 II Wireless Headphones, Certified Refurbished", "price": 15900, "status": "Certified - Refurbished", "shipping": null, "free_returns": true, "items_sold": 0}, {"name": "Wireless Headphones Bluetooth 4.1 Headset Noise Cancelling Over Ear With Mic US", "price": 1299, "status": "Brand New", "shipping": 0, "free_returns": false, "items_sold": null}, {"name": "JBL TUNE 115TWS True Wireless Bluetooth In-Ear Headphones - White", "price": 3244, "status": "Brand New", "shipping": 0, "free_returns": false, "items_sold": 197}, {"name": "Bose SoundSport Wireless In Ear Bluetooth Headphones NFC Bose Black / Blue", "price": 5990, "status": "New (Other)", "shipping": null, "free_returns": true, "items_sold": 1504}, {"name": "Skullcandy INDY FUEL True Wireless Earbuds (Certified Refurbished) BLACK", "price": 2499, "status": "Certified - Refurbished", "shipping": null, "free_returns": true, "items_sold": 0}, {"name": "Kano Headphones", "price": 999, "status": "Brand New", "shipping": 0, "free_returns": true, "items_sold": 0}, {"name": "Bluetooth Neckband Wireless Headphones Mic Headset Stereo Earbuds Earphone", "price": 1189, "status": "Brand New", "shipping": null, "free_returns": true, "items_sold": null}, {"name": "Wireless Bluetooth Handsfree Earphone Earbud Headset For iPhone Samsung Android ", "price": 1149, "status": "Brand New", "shipping": 0, "free_returns": true, "items_sold": null}, {"name": "Sony WH-1000XM4 Wireless Noise-Cancelling Over-the-Ear Headphones - Black", "price": 19999, "status": "Certified - Refurbished", "shipping": 0, "free_returns": true, "items_sold": 0}, {"name": "JBL Tune 215TWS True Wireless Earbud Headphones Pure Bass,Bluetooth - Black", "price": 2999, "status": "Brand New", "shipping": 0, "free_returns": true, "items_sold": null}, {"name": "JBL Tune 500BT Wireless Bluetooth On-Ear Headphones /w Built-In Microphone Black", "price": 3695, "status": "Brand New", "shipping": 0, "free_returns": true, "items_sold": 302}, {"name": "Beats by Dr. Dre Solo 3 Wireless On-Ear Bluetooth Headband Headphones", "price": 10995, "status": "New (Other)", "shipping": 0, "free_returns": true, "items_sold": null}, {"name": "Sony WF-1000XM4 Noise Canceling Wireless Earbud Headphones - Black", "price": 16999, "status": "Certified - Refurbished", "shipping": 0, "free_returns": true, "items_sold": 0}, {"name": "Skullcandy HESH ANC Wireless Over-Ear Headset (Certified Refurbished)-BLACK", "price": 3999, "status": "Certified - Refurbished", "shipping": null, "free_returns": true, "items_sold": 0}, {"name": "Skullcandy INDY EVO Wireless Bluetooth Earbuds  (Certified Refurbished)", "price": 2699, "status": "Certified - Refurbished", "shipping": null, "free_returns": true, "items_sold": 0}, {"name": "Skullcandy SESH XT EVO True Wireless Bluetooth Earbuds (Certified Refurb)-BLACK", "price": 2444, "status": "Certified - Refurbished", "shipping": null, "free_returns": true, "items_sold": 0}, {"name": "Skullcandy Indy True Wireless In-Ear Earbuds - Mint ,Indigo Blue, Black, Green", "price": 1949, "status": "Certified - Refurbished", "shipping": 0, "free_returns": true, "items_sold": 0}, {"name": "Bluetooth Headset Wireless Fitness Stereo Headphones Earphone Mic Earbuds White", "price": 1540, "status": "Brand New", "shipping": 0, "free_returns": true, "items_sold": 551}, {"name": "JBL LIVE 500BT Wireless Bluetooth Over-Ear Headphones with Built-in Microphone", "price": 5999, "status": "Brand New", "shipping": 0, "free_returns": false, "items_sold": 0}, {"name": "Bluetooth 5.0 Wireless Earbuds Headphone Headset Noise Cancelling TWS Waterproof", "price": 1499, "status": "Brand New", "shipping": 0, "free_returns": true, "items_sold": null}, {"name": "Beats by Dr Dre Powerbeats3 In-Ear Wireless Headphones Authentic OEM", "price": 4795, "status": "New (Other)", "shipping": 0, "free_returns": true, "items_sold": 350}, {"name": "Sony WF-1000XM4 Noise Canceling Wireless Earbud Headphones - Silver", "price": 14999, "status": "Certified - Refurbished", "shipping": 0, "free_returns": true, "items_sold": 0}, {"name": "Bluetooth 5.0 Earbuds for iphone Samsung Android Wireless Headphones Waterproof", "price": 3499, "status": "Brand New", "shipping": null, "free_returns": true, "items_sold": null}, {"name": "3.5mm HIFI Super Bass Headset In-Ear Earphone Stereo Earbuds Headphone Wired Mic", "price": 349, "status": "Brand New", "shipping": 0, "free_returns": false, "items_sold": 1436}, {"name": "For iPhone 6 7 8 Plus iPhone X XS MAX XR 11 12 13 Wired Headphone Headset Earbud", "price": 939, "status": "Brand New", "shipping": null, "free_returns": false, "items_sold": null}, {"name": "3.5mm HIFI Super Bass Headset In-Ear Earphone Stereo Earbuds Headphone Wired Mic", "price": 449, "status": "Brand New", "shipping": 0, "free_returns": false, "items_sold": null}, {"name": "Wired Earbuds For Phone Over ear Hook Earphones Philips Headphone Headset-Black", "price": 1499, "status": "Brand New", "shipping": 0, "free_returns": true, "items_sold": 341}, {"name": "Wireless Bluetooth Headphones Earphones Headset Over-Ear FM Radio MIC Foldable", "price": 1399, "status": "Brand New", "shipping": 0, "free_returns": true, "items_sold": null}, {"name": "Super Bass Wireless Bluetooth Headphones Foldable Stereo Earphones Headsets Mic ", "price": 1899, "status": "Brand New", "shipping": 0, "free_returns": true, "items_sold": null}, {"name": "Bluetooth Earbuds for iPhone Samsung Android Wireless Earphone Waterproof", "price": 1289, "status": "Brand New", "shipping": 0, "free_returns": true, "items_sold": null}, {"name": "Replacement Ear Pads Cushion For Beats by Dr Dre Solo 2 Solo 3 Wireless/Wired", "price": 825, "status": "Brand New", "shipping": null, "free_returns": false, "items_sold": null}, {"name": "Skullcandy Sesh Evo True Wireless In-Ear Headset - Black Certified Refurbish", "price": 1999, "status": "Certified - Refurbished", "shipping": 0, "free_returns": true, "items_sold": 0}, {"name": "Bluetooth 5.0 Wireless Earbuds Headphone Headset Noise Cancelling Waterproof TWS", "price": 1059, "status": "Brand New", "shipping": 0, "free_returns": true, "items_sold": 70}, {"name": "Trucker Wireless Bluetooth 5.1 Earpiece Headset Dual Mic Earbud Noise Cancelling", "price": 1798, "status": "Brand New", "shipping": 0, "free_returns": true, "items_sold": null}, {"name": "Bluetooth 5.2 Bone Conduction Headset Wireless Outdoor Sport Open Ear Headphones", "price": 1246, "status": "Brand New", "shipping": 0, "free_returns": true, "items_sold": 326}, {"name": "Soundcore by Anker Life P2 Mini True Wireless Earbuds Bass Bluetooth Headphones", "price": 3399, "status": "Brand New", "shipping": 0, "free_returns": false, "items_sold": 0}, {"name": "TWS Pro 5  In-ear Wireless Earphones", "price": 1399, "status": "Brand New", "shipping": 0, "free_returns": false, "items_sold": null}, {"name": "Bluetooth 5.0 Earbuds for iphone Samsung Android Wireless Headphones Waterproof", "price": 2499, "status": "Brand New", "shipping": 0, "free_returns": true, "items_sold": null}, {"name": "Super Bass Wireless Bluetooth Headphones Foldable Stereo Earphones Headsets Mic", "price": 1614, "status": "Brand New", "shipping": null, "free_returns": true, "items_sold": 215}, {"name": "Bluetooth 5.0 True Wireless Earbuds With Mic Headphones Earhook Sport Waterproof", "price": 2499, "status": "Brand New", "shipping": 0, "free_returns": true, "items_sold": null}, {"name": "Bluedio Fi Bluetooth Earphone TWS Wireless Earbuds Waterproof Stereo Headsets", "price": 1299, "status": "Brand New", "shipping": 0, "free_returns": false, "items_sold": null}, {"name": "Wireless Bluetooth Headphones Over Ear Stereo Super Bass Earphone Headset Mic FM", "price": 1393, "status": "Brand New", "shipping": null, "free_returns": true, "items_sold": null}, {"name": "Bluetooth Headset 5.0 TWS Wireless Earphones Earbuds Headphones Stereo Ear Hook", "price": 1499, "status": "Brand New", "shipping": null, "free_returns": true, "items_sold": null}, {"name": "Sony WH-1000XM4 Over the Ear Noise Cancelling Wireless Headphones", "price": 26995, "status": "Brand New", "shipping": 0, "free_returns": true, "items_sold": 1785}, {"name": "Sony ZX220BT Wireless On-Ear Bluetooth Headphones w/ Built-In Microphone, Black", "price": 2999, "status": "New (Other)", "shipping": 0, "free_returns": true, "items_sold": null}, {"name": "Wireless Bluetooth Earphones For JBL T280 TWS Stereo Earbuds Bass Sound Headset", "price": 1999, "status": "Brand New", "shipping": 0, "free_returns": true, "items_sold": null}, {"name": "Skullcandy INDY ANC Noise Canceling Bluetooth Earbuds (Certified Refurbished)", "price": 3999, "status": "Certified - Refurbished", "shipping": null, "free_returns": true, "items_sold": 0}, {"name": "Skullcandy - Indy True Wireless In-Ear Headphones - Black", "price": 2199, "status": "Certified - Refurbished", "shipping": 0, "free_returns": true, "items_sold": 0}, {"name": "Skullcandy Venue Noise Cancelling Headphones,Over The Ear BT Wireless, ", "price": 4799, "status": "Certified - Refurbished", "shipping": 0, "free_returns": true, "items_sold": 0}, {"name": "Sony - ZX Series Wired On-Ear Headphones - Black", "price": null, "status": "Brand New", "shipping": 549, "free_returns": false, "items_sold": 227}, {"name": "Wireless Bluetooth Earphones For JBL T280 TWS Stereo Earbuds Bass Sound Headset", "price": 2299, "status": "Brand New", "shipping": 0, "free_returns": true, "items_sold": 19}, {"name": "Waterproof Bluetooth 5.0 Earbuds Stereo Sport Wireless Headphones in Ear Headset", "price": 1245, "status": "Brand New", "shipping": 0, "free_returns": true, "items_sold": 239}, {"name": "Wireless Bluetooth Handsfree Earphone earbud Headset For iPhone Samsung Android", "price": 899, "status": "Brand New", "shipping": null, "free_returns": true, "items_sold": null}, {"name": "Skullcandy INDY ANC FUEL Noise Canceling Bluetooth Earbuds-Certified Refurbished", "price": 3999, "status": "Certified - Refurbished", "shipping": null, "free_returns": true, "items_sold": 0}, {"name": "Waterproof Wireless Headphones Bluetooth 5.0 Earbuds cVc6.0 Noise Cancelling Mic", "price": 250, "status": "Brand New", "shipping": 455, "free_returns": true, "items_sold": null}, {"name": "Skullcandy JIB WIRED In-ear Earbuds w/ Mic - NEW - Volume Discounts", "price": 888, "status": "Brand New", "shipping": null, "free_returns": true, "items_sold": null}, {"name": "Skullcandy INDY XT EVO True Wireless Bluetooth Earbuds (Certified Refurb)-BLACK", "price": 2499, "status": "Certified - Refurbished", "shipping": null, "free_returns": true, "items_sold": 0}, {"name": " JLab Audio Studio Wired On-Ear Blue Headphones", "price": 989, "status": "Refurbished", "shipping": null, "free_returns": false, "items_sold": 527}, {"name": "Open Ear Bluetooth Bone Conduction Headphones Wireless Earbuds for Sport Running", "price": 1499, "status": "Brand New", "shipping": 0, "free_returns": true, "items_sold": null}, {"name": "New 5 in 1 Hi-Fi Wireless Stereo Headset Headphone Earphone Headset for PC TV CD", "price": 1199, "status": "Brand New", "shipping": 0, "free_returns": true, "items_sold": null}, {"name": "Skullcandy PUSH XT ULTRA True Wireless Sport Earbuds (Certified Refurbished)", "price": 3333, "status": "Certified - Refurbished", "shipping": null, "free_returns": true, "items_sold": 0}, {"name": "LETSCOM Bluetooth Headphones, IPX7 Waterproof Wireless Sport Earbuds in-Ear", "price": 1999, "status": "Brand New", "shipping": 0, "free_returns": true, "items_sold": null}, {"name": "3.5mm HIFI Super Bass Headset In-Ear Earphone Stereo Earbuds Headphone Wired Mic", "price": 395, "status": "Brand New", "shipping": 0, "free_returns": false, "items_sold": null}, {"name": "Bluetooth Earbuds for iphone Samsung Android Wireless Earphone Noise Cancelling", "price": 1858, "status": "Brand New", "shipping": 0, "free_returns": true, "items_sold": null}, {"name": "JLab Audio Studio Wireless On-Ear Headphones Black", "price": 1475, "status": "New (Other)", "shipping": null, "free_returns": true, "items_sold": null}, {"name": "Genuine Lightning Earphones For Apple iPhone 7 8 Plus 12 Mini 11 Pro Max Earpods", "price": 1699, "status": "Brand New", "shipping": 0, "free_returns": false, "items_sold": 157}, {"name": "LETSCOM Bluetooth Headphones V5.0 IPX7 Waterproof, Wireless Sport Earphones", "price": 1599, "status": "Brand New", "shipping": 0, "free_returns": true, "items_sold": null}, {"name": "Jabra Elite Active 75t True Wireless Earbuds Certified Refurbished", "price": 8299, "status": "Certified - Refurbished", "shipping": 0, "free_returns": true, "items_sold": 0}, {"name": "Skullcandy Dime True Wireless BT Earbuds", "price": 2699, "status": "Brand New", "shipping": 0, "free_returns": false, "items_sold": 0}, {"name": "Bose SoundSport In-ear Wired Headphones 3.5mm For Apple ios & Android- Black Red", "price": 4999, "status": "New (Other)", "shipping": 0, "free_returns": true, "items_sold": 63}, {"name": "NEW 2021 PRO Sport Earbuds Bluetooth 5.0 TWS Headsets Wireless headphones in Ear", "price": 1995, "status": "Brand New", "shipping": 0, "free_returns": true, "items_sold": null}, {"name": "NEW Wired Gaming Headphones Over Ear Headset Earphone With Mic Volume Control US", "price": 1099, "status": "Brand New", "shipping": 0, "free_returns": true, "items_sold": null}, {"name": "5 Pack Black Earbuds Earphones In-Ear Sound Isolating Headphones Flat Cable", "price": 609, "status": "Brand New", "shipping": 0, "free_returns": false, "items_sold": null}, {"name": "Sony WH-CH710N/B Wireless Bluetooth Noise Cancelling Headphones", "price": 4999, "status": "Certified - Refurbished", "shipping": 0, "free_returns": true, "items_sold": 0}, {"name": "Sony WF1000XM3 Noise Canceling True Wireless Earbuds - Black", "price": 5999, "status": "Certified - Refurbished", "shipping": 0, "free_returns": true, "items_sold": 0}, {"name": "Beats by Dr. Dre urBeats 3 In Ear Headphones with Lightning Connector and Mic ", "price": 2995, "status": "New (Other)", "shipping": 0, "free_returns": true, "items_sold": 309}, {"name": "Apple Beats by Dre Powerbeats Pro Charging Case Replacement Beats Genuine", "price": 3794, "status": "Pre-Owned", "shipping": null, "free_returns": true, "items_sold": 732}, {"name": "Jabra Elite 75t True Wireless In-Ear Headphones - Black", "price": 4499, "status": "Refurbished", "shipping": 0, "free_returns": true, "items_sold": 256}, {"name": "JBL  Endurance Run Sport Sweatproof, Fliphook In-Ear Headphones, Green/Black-New", "price": 1799, "status": "Brand New", "shipping": null, "free_returns": true, "items_sold": null}, {"name": "Bluetooth Earbuds for Iphone Samsung Android Wireless Earphone  IPX7 WaterProof", "price": 899, "status": "Brand New", "shipping": 0, "free_returns": false, "items_sold": null}, {"name": "GENUINE Beats by Dr. Dre Studio3 Wireless Bluetooth Over-ear Headphones ", "price": 15900, "status": "New (Other)", "shipping": 0, "free_returns": true, "items_sold": null}, {"name": "Sony MDRE9LP/BLK In-Ear Canal Fashion Color Earbuds Headphones Earphones Black", "price": 899, "status": "Brand New", "shipping": 0, "free_returns": true, "items_sold": 1668}, {"name": "Skullcandy JIB Wireless Bluetooth Black Earbuds  ", "price": 1150, "status": "Brand New", "shipping": 0, "free_returns": false, "items_sold": null}, {"name": "Waterproof Bluetooth 5.0Earbuds Stereo Sport Wireless Headphones in Ear Headset", "price": 1049, "status": "Brand New", "shipping": 0, "free_returns": true, "items_sold": null}, {"name": "Sony WFSP800N/B Truly Wireless Sports In-Ear Noise Canceling Headphones", "price": 4999, "status": "Certified - Refurbished", "shipping": 0, "free_returns": true, "items_sold": 0}, {"name": "Panasonic RP-HJE125 Ergofit In-Ear Headphones Earphones Earbuds FREE SHIPPING!!!", "price": 940, "status": "Brand New", "shipping": null, "free_returns": true, "items_sold": 358}, {"name": "Bluetooth 5.0 Bone Conduction Headset Open Ear Wireless Outdoor Sport Headphones", "price": 1548, "status": "Brand New", "shipping": 0, "free_returns": false, "items_sold": null}, {"name": "Bone Conduction Headphones Bluetooth 5.1 Wireless Open Ear Outdoor Sport Headset", "price": 1498, "status": "Brand New", "shipping": 0, "free_returns": true, "items_sold": null}, {"name": "Genuine Handsfree Wired Headphones Earphones Earbud with Mic For Samsung iPhone", "price": 895, "status": "Brand New", "shipping": 0, "free_returns": false, "items_sold": null}, {"name": "Bluetooth Neckband Headset Wireless Earphone Headphone Mic For iPhone LG Samsung", "price": 1699, "status": "Brand New", "shipping": null, "free_returns": true, "items_sold": null}, {"name": "Earbuds Wireless TWS Bluetooth Headset For Samsung Android Apple iPhone iPod", "price": 1999, "status": "Brand New", "shipping": 0, "free_returns": true, "items_sold": null}, {"name": "Sony Bluetooth Wireless Noise Canceling Sports Headphones SP600N - White", "price": 2999, "status": "Brand New", "shipping": 0, "free_returns": true, "items_sold": 348}, {"name": "Sony Stamina Wireless On Ear Headphones Black", "price": 5800, "status": "Brand New", "shipping": 0, "free_returns": true, "items_sold": 0}, {"name": "HP Wired Stereo Headset with mic Gaming Over ear Headset W LED H200 Headphone", "price": 1999, "status": "Brand New", "shipping": 0, "free_returns": true, "items_sold": null}, {"name": "Bluetooth 5.0 True Wireless Earbuds With Mic Headphones Earhook Sport Waterproof", "price": 2499, "status": "Brand New", "shipping": 0, "free_returns": true, "items_sold": null}, {"name": "Wireless Headset Truck Driver Noise Cancelling Over-Head Bluetooth Headphones US", "price": 1696, "status": "Brand New", "shipping": 0, "free_returns": true, "items_sold": 3467}, {"name": "Skullcandy Jib XT In-Ear Wireless Earbuds (Certified Refurbished)", "price": 888, "status": "Certified - Refurbished", "shipping": null, "free_returns": true, "items_sold": 0}, {"name": "Beats by Dr. Dre Powerbeats 4 \ud83d\udd25 High-Performance Wireless Headphones - Black \ud83d\udd25", "price": 5495, "status": "New (Other)", "shipping": null, "free_returns": true, "items_sold": null}, {"name": "Bluetooth Wireless Headphones On Ear Foldable Stereo Noise Cancelling Headset", "price": 1295, "status": "Brand New", "shipping": null, "free_returns": true, "items_sold": null}, {"name": "Sony WH-CH710N/H Wireless Bluetooth Noise Cancelling Headphones", "price": 4999, "status": "Certified - Refurbished", "shipping": 0, "free_returns": true, "items_sold": 0}, {"name": "Soundcore by Anker Life Q20 Wireless Over Ear Headphones Active Noise Cancelling", "price": 5999, "status": "Brand New", "shipping": 0, "free_returns": false, "items_sold": 0}, {"name": "Bone Conduction Headset Wireless Bluetooth 5.0 Open Ear Outdoor Sport Headphones", "price": 1359, "status": "Brand New", "shipping": null, "free_returns": true, "items_sold": null}, {"name": "Bose SoundSport Wireless In-Ear Bluetooth NFC Headphones Earphones Earbuds", "price": 6499, "status": "New (Other)", "shipping": 0, "free_returns": true, "items_sold": 438}, {"name": "Wireless Bluetooth Earbuds Headset Noise Cancelling TWS Stereo Bass Earphones US", "price": 999, "status": "Brand New", "shipping": 0, "free_returns": true, "items_sold": null}, {"name": "Delton Chroma Wired On-Ear Headphones with Mic, 3.5MM Jack, Foldable Lightweight", "price": 995, "status": "Brand New", "shipping": 0, "free_returns": false, "items_sold": null}, {"name": "Bluetooth 5.0 Wireless Earbuds Headphone Headset Noise Cancelling TWS Waterproof", "price": 1599, "status": "Brand New", "shipping": null, "free_returns": true, "items_sold": null}, {"name": "Wireless Bluetooth Headphones Earphones Headset Over-Ear FM Radio MIC Foldable", "price": 1399, "status": "Brand New", "shipping": 0, "free_returns": true, "items_sold": null}, {"name": "Beats by Dr. Dre Powerbeats Pro Totally Wireless Bluetooth Earphones In Retail", "price": 13495, "status": "New (Other)", "shipping": 0, "free_returns": true, "items_sold": 2428}, {"name": "Wireless Bluetooth Headphone overear Foldable Stereo Super Bass Earphone Headset", "price": 1699, "status": "Brand New", "shipping": null, "free_returns": true, "items_sold": null}, {"name": "Sony - WH-1000XM4 Wireless Noise-Cancelling Over-the-Ear Headphones - Black", "price": null, "status": "Brand New", "shipping": 0, "free_returns": false, "items_sold": null}, {"name": "Bluetooth Earbuds for iPhone Samsung Android Wireless Waterproof F9-32", "price": 1099, "status": "Brand New", "shipping": null, "free_returns": true, "items_sold": null}, {"name": "Beats by Dr. Dre urBeats 3 In Ear Headphones urBeats3 3.5MM Wired Earphones", "price": 2999, "status": "New (Other)", "shipping": 0, "free_returns": true, "items_sold": 123}, {"name": "Sony WF-1000XM3 Wireless Noise Cancelling Headphones / Ear Buds - Black", "price": 6790, "status": "New (Other)", "shipping": 0, "free_returns": false, "items_sold": 104}, {"name": "Earbuds In-Ear Sound Isolating Wired Headphones Headset with Mic & Volume 3.5mm", "price": 349, "status": "Brand New", "shipping": 0, "free_returns": false, "items_sold": 1341}, {"name": "Panasonic RP-HJE125 Ergofit In-Ear Headphones Earphones Earbuds FREE SHIPPING!!!", "price": 940, "status": "Brand New", "shipping": null, "free_returns": true, "items_sold": 358}, {"name": "Sony WFSP800N/L Truly Wireless Sports In-Ear Noise Canceling Headphones", "price": 4999, "status": "Certified - Refurbished", "shipping": 0, "free_returns": true, "items_sold": 0}, {"name": "Sony MDR-ZX110NC Noise Cancelling Headphones", "price": 2999, "status": "Brand New", "shipping": null, "free_returns": true, "items_sold": 783}, {"name": "Beats by Dr. Dre BeatsX Beats X Wireless Bluetooth In-Ear Headphone US", "price": 1999, "status": "Brand New", "shipping": 0, "free_returns": true, "items_sold": null}, {"name": "True Wireless Earbuds Bluetooth 5.0 Waterproof Headset Headphones With Mic Case", "price": 2799, "status": "Brand New", "shipping": null, "free_returns": true, "items_sold": null}, {"name": "Earphones Headphones Headset Earbuds In-Ear Bass Stereo Hi-Fi with MIC Wired", "price": 899, "status": "Brand New", "shipping": 0, "free_returns": true, "items_sold": null}, {"name": "Skullcandy JIB In-Ear Buds Earphones Headphones Headset In Line Mic Wired, Black", "price": 1199, "status": "Brand New", "shipping": 0, "free_returns": false, "items_sold": null}, {"name": "Wireless Bluetooth 5.2 Earpiece Headset Driving Trucker Earbuds Noise Cancelling", "price": 1398, "status": "Brand New", "shipping": 0, "free_returns": true, "items_sold": null}, {"name": "New ListingJabra - Elite 7 Pro True Wireless Noise Canceling In-Ear Headphones - Black", "price": 13500, "status": "New (Other)", "shipping": null, "free_returns": false, "items_sold": null}, {"name": "Bluetooth 5.1 Headphones Bone Conduction Headset Wireless Outdoor Sport Open Ear", "price": 1190, "status": "Brand New", "shipping": 0, "free_returns": false, "items_sold": 0}, {"name": "Skullcandy CRUSHER EVO Wireless Over-Ear Headset (Certified Refurb)-TRUE BLACK", "price": 9999, "status": "Certified - Refurbished", "shipping": null, "free_returns": true, "items_sold": 0}, {"name": "JBL Free X Wireless Headphones Bluetooth Earbuds White True Brand NEW", "price": 4995, "status": "Brand New", "shipping": 0, "free_returns": true, "items_sold": 278}, {"name": "Sony MDRE9LP/BLK In-Ear Canal Fashion Color Earbuds Headphones Earphones Black", "price": 899, "status": "Brand New", "shipping": 0, "free_returns": true, "items_sold": 1668}, {"name": "Skullcandy Ink'd In-Ear Buds Bluetooth Wireless Headphones w/Mic Gray/Miami Mint", "price": 2299, "status": "Brand New", "shipping": null, "free_returns": false, "items_sold": null}, {"name": "Mini Bluetooth 5.0 Headset TWS Wireless Earphones Stereo Headphones Earbuds", "price": 1359, "status": "Brand New", "shipping": 0, "free_returns": false, "items_sold": 183}, {"name": "Mackie MC-100 Closed-Back, Over-Ear Headphones", "price": 2999, "status": "Brand New", "shipping": 0, "free_returns": true, "items_sold": 101}, {"name": "Bluetooth Wireless Headphones On Ear Foldable Stereo Noise Cancelling Headset", "price": 1199, "status": "Brand New", "shipping": null, "free_returns": false, "items_sold": null}, {"name": "NEW Sentry HO415 Lightweight Digital Stereo Headphones FREE SHIPPING", "price": 599, "status": "Brand New", "shipping": 0, "free_returns": false, "items_sold": null}, {"name": "Califone 3068AV Switchable Stereo/Mono Headphones Brand New", "price": 1099, "status": "Brand New", "shipping": 0, "free_returns": false, "items_sold": 1050}, {"name": "Bone Conduction Headset Wireless Bluetooth 5.0 Open Ear Outdoor Sport Headphones", "price": 1359, "status": "Brand New", "shipping": null, "free_returns": true, "items_sold": null}, {"name": "Jabra Elite Active 75t True Wireless Sports Headphones Voice Assistant in Colors", "price": 6999, "status": "New (Other)", "shipping": 0, "free_returns": true, "items_sold": 68}, {"name": "Skullcandy JIB DUB In-Ear Buds EarBuds Stereo Earphones Headphones (Black)", "price": 999, "status": "Brand New", "shipping": null, "free_returns": false, "items_sold": null}, {"name": "Skullcandy INDY TRUE Wireless Bluetooth Earbuds w/ Mic (Cert Refurbished)-BLACK", "price": 2199, "status": "Certified - Refurbished", "shipping": null, "free_returns": true, "items_sold": 0}, {"name": "Akg Type-C Samsung Galaxy S21 S20 Ultra Note 10 20 Earphones Headphones Earbuds", "price": 999, "status": "Brand New", "shipping": 0, "free_returns": true, "items_sold": null}, {"name": "OEM Orginal Samsung AKG Stereo Headphones Headphone Earphones In Ear Earbuds Lot", "price": 15999, "status": "Brand New", "shipping": 0, "free_returns": true, "items_sold": 143}, {"name": "Bluetooth 5.0 Wireless Earbuds Headphone Headset Noise Cancelling TWS Waterproof", "price": 1498, "status": "Brand New", "shipping": null, "free_returns": false, "items_sold": 6931}, {"name": "Foldable Wireless Bluetooth Headphones Super Bass Stereo Earphones Headsets Mic", "price": 1369, "status": "Brand New", "shipping": null, "free_returns": true, "items_sold": 28}, {"name": "Mpow Flame Lite Ear-hook Bluetooth 5.0 Earbuds Wireless Headset Sport Headphones", "price": 1681, "status": "Brand New", "shipping": 0, "free_returns": false, "items_sold": null}, {"name": "Mpow Wireless Bluetooth Noise Cancelling Headphones Foldable Over Ear Headset", "price": 2499, "status": "Brand New", "shipping": 0, "free_returns": false, "items_sold": null}, {"name": " JLab Audio Studio Wired On-Ear Headphones - Blue", "price": 1099, "status": "Refurbished", "shipping": null, "free_returns": false, "items_sold": null}, {"name": "Sony WH-1000XM4 Wireless Noise-Cancelling Over-the-Ear Headphones Midnight Blue", "price": 19999, "status": "Certified - Refurbished", "shipping": 0, "free_returns": true, "items_sold": 0}, {"name": "Sony WI-XB400 Extra Bass Wireless In-Ear Headphones WIXB400 - NEW", "price": 2695, "status": "New (Other)", "shipping": null, "free_returns": true, "items_sold": 293}, {"name": "Sony WF-1000XM4 True Wireless Noise Canceling In Ear Headphones Black", "price": 22000, "status": "Brand New", "shipping": 0, "free_returns": false, "items_sold": 0}, {"name": "Bluetooth Headset Wireless Trucker Driving Office Headphone Noise Cancelling Mic", "price": 2598, "status": "Brand New", "shipping": 0, "free_returns": true, "items_sold": null}, {"name": "Wireless Bluetooth Headphones Super Bass Foldable Stereo Earphones Headsets Mic", "price": 2099, "status": "Brand New", "shipping": 0, "free_returns": false, "items_sold": null}, {"name": "Skullcandy VENUE Active Noise Canceling Wireless Headphones-Refurb-BLACK", "price": 5999, "status": "Certified - Refurbished", "shipping": null, "free_returns": true, "items_sold": 0}, {"name": "Sony WF-1000XM3 Bluetooth Noise Canceling In-Ear True Wireless Headphones Black", "price": 4500, "status": "Refurbished", "shipping": 850, "free_returns": false, "items_sold": 0}, {"name": "Bose Soundsport Wired In-Ear Headphones 3.5mm For IOS Android Version- Black Red", "price": 4999, "status": "New (Other)", "shipping": 0, "free_returns": true, "items_sold": 52}, {"name": "Bose True Wireless Bluetooth Sport Earbuds Headphones - White | Blue | Black", "price": 14900, "status": "Brand New", "shipping": 0, "free_returns": false, "items_sold": 150}, {"name": "OneOdio Adapter-free Closed Back Over-Ear Wired Headphone Studio Pro-10 Black", "price": 3198, "status": "Brand New", "shipping": 0, "free_returns": true, "items_sold": null}, {"name": "Wireless Earbuds Bluetooth 5.0 Headsets Headphones Bass Stereo IPX8 Waterproof", "price": 1685, "status": "Brand New", "shipping": 0, "free_returns": true, "items_sold": 1290}, {"name": "Mpow MX3 Bluetooth 5.0 Earbuds Headset Wireless Earphones for iphone Android", "price": 1399, "status": "Brand New", "shipping": 0, "free_returns": true, "items_sold": null}, {"name": "Wireless Earbuds,Bluetooth 5.0 Earbuds Touch in-Ear Wireless Earphones,24 Hours ", "price": 1790, "status": "Brand New", "shipping": null, "free_returns": true, "items_sold": 0}, {"name": "Wireless Bluetooth Stereo Foldable Earphones Super Bass Headphones Headsets Mic", "price": 3183, "status": "Brand New", "shipping": 0, "free_returns": true, "items_sold": null}, {"name": "Bluetooth 5.1 Headphones Bone Conduction Stereo Wireless Sport Headsets With Mic", "price": 1299, "status": "Brand New", "shipping": 0, "free_returns": true, "items_sold": 0}, {"name": "Bone Conduction Wireless Bluetooth Headphones Sports Open Ear Headset with Mic", "price": 1499, "status": "Brand New", "shipping": null, "free_returns": true, "items_sold": null}, {"name": "Skullcandy INDY FUEL Wireless In-Ear Earphones w/Mic (Cert Refurbish)-CHILL GRAY", "price": 2444, "status": "Certified - Refurbished", "shipping": null, "free_returns": true, "items_sold": 0}, {"name": "Ear Pad Cushions Replacement For Beats Dre Solo 2 Solo3 Studio3 On-Ear Wireless", "price": 1099, "status": "Brand New", "shipping": null, "free_returns": true, "items_sold": null}, {"name": "Bose Frames Rondo, Certified Refurbished", "price": 9900, "status": "Certified - Refurbished", "shipping": null, "free_returns": true, "items_sold": 0}, {"name": "New ListingJBL TUNE 500BT Wireless Bluetooth On-ear Headphones Black", "price": 3999, "status": "Brand New", "shipping": 0, "free_returns": false, "items_sold": null}, {"name": "Sony C400 In-Ear Earbuds Headphones Bluetooth Neckband Headset Mic, Black", "price": 2499, "status": "New (Other)", "shipping": 0, "free_returns": true, "items_sold": null}, {"name": "Skullcandy SESH EVO True Wireless Bluetooth in-Ear Earbud (Cert Refurb)-Mint", "price": 2499, "status": "Certified - Refurbished", "shipping": null, "free_returns": true, "items_sold": 0}, {"name": "Bluetooth Headset 5.1 TWS Wireless Earphones Earbuds Headphones Stereo Ear Hook", "price": 2499, "status": "Brand New", "shipping": 0, "free_returns": true, "items_sold": null}, {"name": "Sony RF400 Wireless Home Theater Headphones (WH-RF400) Black", "price": 2999, "status": "New (Other)", "shipping": 0, "free_returns": true, "items_sold": 274}, {"name": "Aftershokz AIR wireless bone conduction headphonesAS650 Grey Tested w/cord&pouch", "price": 4495, "status": "Pre-Owned", "shipping": 0, "free_returns": false, "items_sold": 0}, {"name": "Waterproof Bluetooth 5.0 Earbuds Stereo Sport Wireless Headphones in Ear Headset", "price": 1199, "status": "Brand New", "shipping": null, "free_returns": true, "items_sold": null}, {"name": "Aftershokz OPENMOVE AS660 Bone Conduction Bluetooth Open Ear Headphones ", "price": 7995, "status": "Brand New", "shipping": null, "free_returns": true, "items_sold": 167}, {"name": "LETSCOM Bluetooth Headphones,  Wireless Sport Earbuds in-Ear  HiFi Stereo sound", "price": 1699, "status": "Brand New", "shipping": 0, "free_returns": true, "items_sold": null}, {"name": "Skullcandy CASSETTE WIRELESS On-Ear Headphones (Certified Refurbished)", "price": 2395, "status": "Certified - Refurbished", "shipping": null, "free_returns": true, "items_sold": 0}, {"name": "Super Bass Wireless Bluetooth Headphones Foldable Stereo Earphones Headsets Mic", "price": 1299, "status": "Brand New", "shipping": 0, "free_returns": true, "items_sold": 0}, {"name": "Bone Conduction Headset Wireless Bluetooth 5.0 Outdoor Sport Open Ear Headphones", "price": 2199, "status": "Brand New", "shipping": 0, "free_returns": false, "items_sold": null}, {"name": "Sony WF-SP800N Truly Wireless Sports In-Ear Noise Canceling Headphones - Black", "price": 3800, "status": "Refurbished", "shipping": 425, "free_returns": false, "items_sold": 0}, {"name": "New ListingBose SoundSport Wireless Bluetooth Headphones Earbuds Best Price Blue", "price": 4450, "status": "Pre-Owned", "shipping": 0, "free_returns": false, "items_sold": null}, {"name": "One 1x Lost Replacement Part - Skullcandy Indy EVO or Fuel or ANC Headphones", "price": 4595, "status": "Pre-Owned", "shipping": 0, "free_returns": false, "items_sold": 0}, {"name": "SoundSport In-Ear Earphones Headset For  Apple ios Version Color Black", "price": 3999, "status": "Refurbished", "shipping": 0, "free_returns": false, "items_sold": null}, {"name": "Sony WF-1000XM3 Wireless Noise Cancelling Headphones / Ear Buds - Black (READ)", "price": 4100, "status": "Pre-Owned", "shipping": 0, "free_returns": false, "items_sold": 0}, {"name": "Over The Ear Headphones Wired Black Flexible Clear Sound Stereophone 3.5mm", "price": 2599, "status": "Brand New", "shipping": null, "free_returns": true, "items_sold": 0}, {"name": "Bluetooth Wireless Headphones On Ear Foldable Stereo Noise Cancelling Headset", "price": 1058, "status": "Brand New", "shipping": 0, "free_returns": true, "items_sold": null}, {"name": "Sony WI-C310 Wireless Bluetooth Earbuds Neckband Headphones WIC310 - NEW ", "price": 1995, "status": "New (Other)", "shipping": null, "free_returns": true, "items_sold": 114}, {"name": "SONY WF-1000XM3 True Wireless Noise Canceling Headphones SILVER WF1000XM3/S", "price": 4998, "status": "Pre-Owned", "shipping": 0, "free_returns": false, "items_sold": null}, {"name": "Skullcandy Icon Wireless Bluetooth Over The Ear Headphones - Black", "price": 3499, "status": "Brand New", "shipping": 0, "free_returns": true, "items_sold": null}, {"name": "Bluetooth 5.0 Headset Wireless Earphones Stereo Noise Reduction Sport Ear-hook", "price": 2395, "status": "Brand New", "shipping": 0, "free_returns": true, "items_sold": null}, {"name": "Walker\u2019s Razor Slim GWP Electronic Hearing Protection & Sound Amp Ear Muffs", "price": 3995, "status": "Brand New", "shipping": 0, "free_returns": true, "items_sold": null}, {"name": "Bluetooth 5.0 Earpiece Driving Trucker Wireless Headset Earbuds Noise Cancelling", "price": 1398, "status": "Brand New", "shipping": 0, "free_returns": false, "items_sold": null}, {"name": "Bose SoundSport In Ear 3.5mm Wired Headphones for IOS Android ", "price": 2999, "status": "Refurbished", "shipping": 0, "free_returns": false, "items_sold": null}, {"name": "Waterproof  Earbuds Beats Sports Wireless Headphones in Ear Headset w/Mic IPX7", "price": 1583, "status": "Brand New", "shipping": 0, "free_returns": false, "items_sold": null}, {"name": "Skullcandy SESH EVO True Wireless Bluetooth in-Ear Earbud (Cert Refurb)-BLACK", "price": 2499, "status": "Certified - Refurbished", "shipping": null, "free_returns": true, "items_sold": 0}, {"name": "Skullcandy SESH TRUE Wireless In-ear Bluetooth Earbuds (Cert Refurb)-INDIGO/BLUE", "price": 1999, "status": "Certified - Refurbished", "shipping": null, "free_returns": true, "items_sold": 0}, {"name": "New ListingJLab  True Wireless In-Ear Headphones - New/Open Box", "price": 3450, "status": "New (Other)", "shipping": null, "free_returns": false, "items_sold": null}, {"name": "Beats by Dr. Dre Powerbeats3 Wireless In Ear Headphones [Certified Refurbished]", "price": 6195, "status": "Certified - Refurbished", "shipping": null, "free_returns": true, "items_sold": 0}, {"name": "Anker Soundcore Life U2 Bluetooth Headphones Noise Cancelling Wireless Earbuds", "price": 4299, "status": "Brand New", "shipping": 0, "free_returns": false, "items_sold": 0}, {"name": "Wireless Bluetooth 5.0 Earpiece Noise Cancelling Headset Driving Trucker Earbuds", "price": 1499, "status": "Brand New", "shipping": 0, "free_returns": false, "items_sold": 118}, {"name": "JBL TUNE 500BT Wireless On-Ear Headphones (Black)", "price": 1999, "status": "Pre-Owned", "shipping": null, "free_returns": true, "items_sold": 388}, {"name": "Bose Soundsport Free Wireless Headphones Replacement Earbuds/Charging Case Color", "price": 6495, "status": "Pre-Owned", "shipping": 0, "free_returns": false, "items_sold": 337}, {"name": "OEM Apple iPhone 7 8 X XR XS 11 12 Series Original EarPods Headphones Lightning", "price": 1475, "status": "Brand New", "shipping": null, "free_returns": false, "items_sold": null}, {"name": "Wireless Bluetooth 5.0 Headset Cat Rabbit Ear LED w/Mic Headphone For Kids Girls", "price": 1448, "status": "Brand New", "shipping": 0, "free_returns": false, "items_sold": null}, {"name": "Bluetooth Neckband Headset Wireless Earphone Headphone Mic For iPhone LG Samsung", "price": 1899, "status": "Brand New", "shipping": 0, "free_returns": true, "items_sold": null}, {"name": "JBL LIVE 650BTNC Wireless Over-ear Noise-cancelling Headphones, Black", "price": 9795, "status": "Certified - Refurbished", "shipping": 0, "free_returns": true, "items_sold": 0}, {"name": "TCL SOCL Series Wired  In-Ear Headphones with Mic & Call Functions", "price": 399, "status": "Brand New", "shipping": 0, "free_returns": false, "items_sold": null}, {"name": "Beats by Dr. Dre Studio3 Wireless Over Ear Headphones - Black/Red", "price": 8850, "status": "Refurbished", "shipping": 595, "free_returns": false, "items_sold": 0}, {"name": "Super Bass Wireless Bluetooth Headphones Foldable Stereo Earphones Headsets Mic", "price": 1359, "status": "Brand New", "shipping": 0, "free_returns": true, "items_sold": null}, {"name": "Mpow Flame2 Wireless Bluetooth 5.0 Headset Sport Headphones Ear Hook Earphones", "price": 1233, "status": "Brand New", "shipping": 0, "free_returns": false, "items_sold": null}, {"name": "Panasonic RP-HT21 On Ear Lightweight Headphones with XBS, Black/Silver", "price": 998, "status": "Brand New", "shipping": 0, "free_returns": true, "items_sold": null}, {"name": "Sennheiser Wireless Noise Cancelling Headphones HD 450BT Certified Refurbished", "price": 9995, "status": "Certified - Refurbished", "shipping": 0, "free_returns": true, "items_sold": 0}, {"name": "Beats by Dr. Dre - Beats Studio\u00b3 Wireless Noise Cancelling Headphones - Matte...", "price": null, "status": "Brand New", "shipping": 0, "free_returns": false, "items_sold": null}, {"name": "Sony Wireless WI-C300 Headphones In-Ear Earbuds Bluetooth Earphone WIC300 (NEW)", "price": 1596, "status": "New (Other)", "shipping": null, "free_returns": true, "items_sold": 207}, {"name": "NEW Beats by Dr. Dre Powerbeats 3 In-Ear Wireless Bluetooth Headphones - Black", "price": 4995, "status": "New (Other)", "shipping": 0, "free_returns": true, "items_sold": null}, {"name": "Mini Bluetooth 5.0 Wireless Headset TWS Earphones Stereo Headphones Earbuds", "price": 1239, "status": "Brand New", "shipping": null, "free_returns": false, "items_sold": null}, {"name": "Soundcore Liberty 2 Wireless Earbuds Bluetooth 5.0 In-Ear Headphones Clear Calls", "price": 4999, "status": "Brand New", "shipping": 0, "free_returns": false, "items_sold": 0}, {"name": "Bose SoundSport Wireless NFC Earphones In Ear Bluetooth Headphones -Black", "price": 5499, "status": "New (Other)", "shipping": 0, "free_returns": true, "items_sold": 138}, {"name": "NEW Mini Stereo Lightweight Headphones On-ear with 4 ft. Cord @ FREE FAST SHIP", "price": 950, "status": "Brand New", "shipping": 0, "free_returns": true, "items_sold": 234}, {"name": "Jabra Elite 75t True Wireless In-Ear Headphones - Gold Beige", "price": 4499, "status": "Refurbished", "shipping": 0, "free_returns": true, "items_sold": 0}, {"name": "HIFI Super Bass Headset 3.5mm In-Ear Earphone Stereo Earbuds Headphone Wired", "price": 368, "status": "Brand New", "shipping": null, "free_returns": false, "items_sold": 307}, {"name": "JBL Headphones HARMAN TUNE 500 Pure Bass Sound Wired On-Ear Remote Mic Bass", "price": 2650, "status": "Brand New", "shipping": 0, "free_returns": false, "items_sold": 0}, {"name": "Bose SoundSport Wireless In Ear Bluetooth Headphones", "price": 5799, "status": "New (Other)", "shipping": null, "free_returns": true, "items_sold": null}, {"name": "2pcs For Samsung Handsfree Wired Headphones Earphones Earbud with Mic-White", "price": 949, "status": "Brand New", "shipping": null, "free_returns": true, "items_sold": 4250}, {"name": "Wireless Bluetooth 5.0 Over Ear Headphone Stereo Noise Canceling Headset w Mic ", "price": 2096, "status": "Brand New", "shipping": 0, "free_returns": true, "items_sold": null}, {"name": "Wired 3.5mm LED Headphones With Mic Stereo Super Bass Headset Over the Ear", "price": 2971, "status": "Brand New", "shipping": 0, "free_returns": true, "items_sold": null}]